twaw/__init__.py
twaw/twaw.py
time_weighted_average_for_water-0.1.0.dist-info/LICENSE
time_weighted_average_for_water-0.1.0.dist-info/METADATA
time_weighted_average_for_water-0.1.0.dist-info/WHEEL
time_weighted_average_for_water-0.1.0.dist-info/top_level.txt
time_weighted_average_for_water-0.1.0.dist-info/RECORD
