Metadata-Version: 2.1
Name: time-weighted-average-for-water
Version: 0.1.0
Summary: A tool to calculate time weighted average for water level / flow.
Home-page: https://github.com/longavailable/time-weighted-average-for-water
Author: Xiaolong "Bruce" Liu
Author-email: liuxiaolong125@gmail.com
Classifier: Programming Language :: Python :: 3
Classifier: License :: OSI Approved :: MIT License
Classifier: Operating System :: OS Independent
Requires-Python: >=3.6
License-File: LICENSE
Requires-Dist: numpy
Requires-Dist: pandas
